setup.py
matrix_alg/__init__.py
matrix_alg/matrix_alg.py
matrix_alg_jdf.egg-info/PKG-INFO
matrix_alg_jdf.egg-info/SOURCES.txt
matrix_alg_jdf.egg-info/dependency_links.txt
matrix_alg_jdf.egg-info/not-zip-safe
matrix_alg_jdf.egg-info/top_level.txt