Metadata-Version: 1.0
Name: matrix-alg-jdf
Version: 1.0
Summary: Matrix algebra
Home-page: UNKNOWN
Author: UNKNOWN
Author-email: UNKNOWN
License: UNKNOWN
Platform: UNKNOWN
